gief/__init__.py
gief/__main__.py
gief/gief.py
gief-0.0.3.data/scripts/gief
gief-0.0.3.dist-info/LICENSE
gief-0.0.3.dist-info/METADATA
gief-0.0.3.dist-info/WHEEL
gief-0.0.3.dist-info/top_level.txt
gief-0.0.3.dist-info/RECORD
